fireplace/__init__.py
fireplace/actions.py
fireplace/aura.py
fireplace/card.py
fireplace/config.py
fireplace/deck.py
fireplace/deepcopy.py
fireplace/entity.py
fireplace/enums.py
fireplace/events.py
fireplace/exceptions.py
fireplace/game.py
fireplace/logging.py
fireplace/managers.py
fireplace/player.py
fireplace/rules.py
fireplace/targeting.py
fireplace/utils.py
fireplace/brawls/__init__.py
fireplace/cards/__init__.py
fireplace/cards/cardlist.py
fireplace/cards/neutral.py
fireplace/cards/utils.py
fireplace/cards/Saviors/__init__.py
fireplace/cards/Saviors/hunter.py
fireplace/cards/Saviors/mage.py
fireplace/cards/Saviors/neutral.py
fireplace/cards/Saviors/paladin.py
fireplace/cards/Shadows/__init__.py
fireplace/cards/Shadows/hunter.py
fireplace/cards/Shadows/mage.py
fireplace/cards/Shadows/neutral.py
fireplace/cards/Shadows/paladin.py
fireplace/cards/alterac/__init__.py
fireplace/cards/alterac/demon_hunter.py
fireplace/cards/alterac/druid.py
fireplace/cards/alterac/hunter.py
fireplace/cards/alterac/mage.py
fireplace/cards/alterac/neutral.py
fireplace/cards/alterac/paladin.py
fireplace/cards/alterac/priest.py
fireplace/cards/alterac/rogue.py
fireplace/cards/alterac/shaman.py
fireplace/cards/alterac/warlock.py
fireplace/cards/alterac/warrior.py
fireplace/cards/aoo/__init__.py
fireplace/cards/aoo/demon_hunter.py
fireplace/cards/aoo/druid.py
fireplace/cards/aoo/hunter.py
fireplace/cards/aoo/mage.py
fireplace/cards/aoo/neutral.py
fireplace/cards/aoo/paladin.py
fireplace/cards/aoo/warrior.py
fireplace/cards/barrens/__init__.py
fireplace/cards/barrens/demon_hunter.py
fireplace/cards/barrens/druid.py
fireplace/cards/barrens/hunter.py
fireplace/cards/barrens/mage.py
fireplace/cards/barrens/neutral.py
fireplace/cards/barrens/paladin.py
fireplace/cards/barrens/warrior.py
fireplace/cards/bigWarrior/__init__.py
fireplace/cards/bigWarrior/bigWarrior.py
fireplace/cards/blackrock/__init__.py
fireplace/cards/blackrock/adventure.py
fireplace/cards/blackrock/brawl.py
fireplace2-1.0.2.dist-info/LICENSE.md
fireplace2-1.0.2.dist-info/METADATA
fireplace2-1.0.2.dist-info/WHEEL
fireplace2-1.0.2.dist-info/top_level.txt
fireplace2-1.0.2.dist-info/zip-safe
fireplace2-1.0.2.dist-info/RECORD
