Metadata-Version: 2.1
Name: fireplace2
Version: 1.0.2
Summary: Hearthstone engine reimplementation and simulator
Home-page: https://hearthsim.info/fireplace/
Author: Jerome Leclanche
Author-email: jerome@leclan.ch
License: UNKNOWN
Download-URL: https://github.com/HearthSim/fireplace/tarball/master
Platform: UNKNOWN
Classifier: Development Status :: 2 - Pre-Alpha
Classifier: Intended Audience :: Developers
Classifier: License :: OSI Approved :: GNU Affero General Public License v3 or later (AGPLv3+)
Classifier: Programming Language :: Python
Classifier: Programming Language :: Python :: 3
Classifier: Programming Language :: Python :: 3.8
Classifier: Topic :: Games/Entertainment :: Simulation
License-File: LICENSE.md
Requires-Dist: hearthstone
